ai4free/BasedGPT.py
ai4free/Berlin4h.py
ai4free/Blackbox.py
ai4free/ChatGPTUK.py
ai4free/Cohere.py
ai4free/Deepinfra.py
ai4free/KOBOLDAI.py
ai4free/OpenGPT.py
ai4free/Openai.py
ai4free/Phind.py
ai4free/ThinkAnyAI.py
ai4free/__init__.py
ai4free/groq.py
ai4free/leo.py
ai4free/perplexity.py
ai4free/reka.py
ai4free/yep.py
ai4free/you.py
ai4free-0.7.dist-info/LICENSE.md
ai4free-0.7.dist-info/METADATA
ai4free-0.7.dist-info/WHEEL
ai4free-0.7.dist-info/top_level.txt
ai4free-0.7.dist-info/RECORD
