Metadata-Version: 2.1
Name: ai4free
Version: 0.7
Summary: collection of free AI provides
Author: OEvortex
Author-email: helpingai5@gmail.com
License: HelpingAI Simplified Universal License
Project-URL: Source, https://github.com/Devs-Do-Code/ai4free
Project-URL: Tracker, https://github.com/Devs-Do-Code/ai4free/issues
Project-URL: YouTube, https://youtube.com/@OEvortex
Project-URL: Youtube, https://www.youtube.com/@DevsDoCode
Classifier: Development Status :: 5 - Production/Stable
Classifier: Intended Audience :: Developers
Classifier: License :: Other/Proprietary License
Classifier: Operating System :: OS Independent
Classifier: Programming Language :: Python :: 3
Classifier: Programming Language :: Python :: 3.8
Classifier: Programming Language :: Python :: 3.9
Classifier: Programming Language :: Python :: 3.10
Classifier: Programming Language :: Python :: 3.11
Classifier: Programming Language :: Python :: 3.12
Classifier: Programming Language :: Python :: Implementation :: CPython
Classifier: Topic :: Internet :: WWW/HTTP :: Indexing/Search
Classifier: Topic :: Software Development :: Libraries :: Python Modules
License-File: LICENSE.md
Requires-Dist: tls-client
Requires-Dist: webscout
